microagent/__init__.py
microagent/abc.py
microagent/agent.py
microagent/broker.py
microagent/bus.py
microagent/hooks.py
microagent/launcher.py
microagent/py.typed
microagent/queue.py
microagent/signal.py
microagent/timer.py
microagent/utils.py
microagent/tools/__init__.py
microagent/tools/amqp.py
microagent/tools/kafka.py
microagent/tools/mocks.py
microagent/tools/redis.py
microagent-1.7.3.dist-info/LICENSE.md
microagent-1.7.3.dist-info/METADATA
microagent-1.7.3.dist-info/WHEEL
microagent-1.7.3.dist-info/entry_points.txt
microagent-1.7.3.dist-info/top_level.txt
microagent-1.7.3.dist-info/RECORD
