Metadata-Version: 2.1
Name: microagent
Version: 1.7.3
Summary: Tool for agent ecosystem
Author-email: Dmitriy Vlasov <scailer@yandex.ru>
License: MIT License
Project-URL: Homepage, https://github.com/scailer/microagent
Project-URL: Documentation, https://microagent.readthedocs.io/en/stable/
Project-URL: Repository, https://github.com/scailer/microagent.git
Project-URL: Changelog, https://github.com/scailer/microagent/blob/master/CHANGELOG.rst
Keywords: async,pubsub,queue,agent,periodic,cron
Classifier: Development Status :: 5 - Production/Stable
Classifier: Environment :: Plugins
Classifier: Intended Audience :: Developers
Classifier: License :: OSI Approved :: MIT License
Classifier: Programming Language :: Python
Classifier: Programming Language :: Python :: 3
Classifier: Programming Language :: Python :: 3.10
Classifier: Programming Language :: Python :: 3.11
Classifier: Programming Language :: Python :: 3.12
Classifier: Topic :: Software Development :: Libraries :: Python Modules
Classifier: Framework :: AsyncIO
Requires-Python: >=3.10
License-File: LICENSE.md
Provides-Extra: amqp
Requires-Dist: aiormq ==6.8.* ; extra == 'amqp'
Provides-Extra: dev
Requires-Dist: pytest ; extra == 'dev'
Requires-Dist: pytest-runner ; extra == 'dev'
Requires-Dist: pytest-asyncio ; extra == 'dev'
Requires-Dist: pytest-cov ; extra == 'dev'
Requires-Dist: coverage ; extra == 'dev'
Requires-Dist: mypy ; extra == 'dev'
Requires-Dist: ruff ; extra == 'dev'
Requires-Dist: redis ==5.* ; extra == 'dev'
Requires-Dist: aiormq ==6.8.* ; extra == 'dev'
Requires-Dist: aiokafka ==0.10.* ; extra == 'dev'
Provides-Extra: kafka
Requires-Dist: aiokafka ==0.10.* ; extra == 'kafka'
Provides-Extra: redis
Requires-Dist: redis[hiredis] ==5.* ; extra == 'redis'
